django_jwt_auth_middleware/__init__.py
django_jwt_auth_middleware/apps.py
django_jwt_auth_middleware/auth.py
django_jwt_auth_middleware/settings.py
django_jwt_auth_middleware/urls.py
django_jwt_auth_middleware/views.py
django_jwt_auth_middleware-0.1.1.dist-info/LICENSE
django_jwt_auth_middleware-0.1.1.dist-info/METADATA
django_jwt_auth_middleware-0.1.1.dist-info/WHEEL
django_jwt_auth_middleware-0.1.1.dist-info/top_level.txt
django_jwt_auth_middleware-0.1.1.dist-info/RECORD
