Metadata-Version: 2.1
Name: django-jwt-auth-middleware
Version: 0.1.1
Summary: Django middleware for utilizing JWT for authentication.
Home-page: https://www.example.com/
Author: Jarod Latta
Author-email: Jarod Latta <jrlatta512@gmail.com>
License: MIT License        
Project-URL: Homepage, https://gitlab.com/sithon512/django-jwt-auth-middleware
Project-URL: Bug Tracker, https://gitlab.com/sithon512/django-jwt-auth-middleware/-/issues
Classifier: Programming Language :: Python :: 3
Classifier: License :: OSI Approved :: MIT License
Classifier: Operating System :: OS Independent
Requires-Python: >=3.10
License-File: LICENSE
Requires-Dist: asgiref (>=3.5)
Requires-Dist: Django (>=4.0)
Requires-Dist: django-appconf (>=1.0.5)
Requires-Dist: pyjwt (>=2.4)
Requires-Dist: sqlparse (==0.4.2)
Requires-Dist: tzdata (>=2022.1)
